prodml22/__init__.py
prodml22/absolute_pressure.py
prodml22/absolute_pressure_interval.py
prodml22/absorbed_dose_measure.py
prodml22/absorbed_dose_measure_ext.py
prodml22/absorbed_dose_uom.py
prodml22/abstract2d_crs.py
prodml22/abstract2d_position.py
prodml22/abstract3d_position.py
prodml22/abstract_active_object.py
prodml22/abstract_activity_parameter.py
prodml22/abstract_analysis.py
prodml22/abstract_attenuation_measure.py
prodml22/abstract_boolean_array.py
prodml22/abstract_cable.py
prodml22/abstract_cartesian2d_position.py
prodml22/abstract_compositional_eo_smodel.py
prodml22/abstract_compositional_model.py
prodml22/abstract_compositional_viscosity_model.py
prodml22/abstract_compound_crs.py
prodml22/abstract_compound_position.py
prodml22/abstract_correlation_gas_viscosity_model.py
prodml22/abstract_correlation_model.py
prodml22/abstract_correlation_viscosity_bubble_point_model.py
prodml22/abstract_correlation_viscosity_dead_model.py
prodml22/abstract_correlation_viscosity_model.py
prodml22/abstract_correlation_viscosity_undersaturated_model.py
prodml22/abstract_date_time_class.py
prodml22/abstract_deconvolution_output.py
prodml22/abstract_disposition.py
prodml22/abstract_dts_equipment.py
prodml22/abstract_elevation.py
prodml22/abstract_fiber_facility.py
prodml22/abstract_floating_point_array.py
prodml22/abstract_flow_test_data.py
prodml22/abstract_fluid_component.py
prodml22/abstract_gas_produced_ratio_volume.py
prodml22/abstract_geographic2d_crs.py
prodml22/abstract_graphical_information.py
prodml22/abstract_growing_object.py
prodml22/abstract_growing_object_part.py
prodml22/abstract_horizontal_coordinates.py
prodml22/abstract_integer_array.py
prodml22/abstract_interval.py
prodml22/abstract_liquid_dropout_perc_volume.py
prodml22/abstract_md_growing_object.py
prodml22/abstract_md_growing_part.py
prodml22/abstract_md_interval_growing_part.py
prodml22/abstract_measure_data.py
prodml22/abstract_model_section.py
prodml22/abstract_numeric_array.py
prodml22-1.0.0.dist-info/LICENSE
prodml22-1.0.0.dist-info/WHEEL
prodml22-1.0.0.dist-info/METADATA
prodml22-1.0.0.dist-info/RECORD
